password_reset_token/__init__.py
password_reset_token/defaults.py
password_reset_token/token.py
password_reset_token-0.0.4.dist-info/LICENSE
password_reset_token-0.0.4.dist-info/METADATA
password_reset_token-0.0.4.dist-info/WHEEL
password_reset_token-0.0.4.dist-info/top_level.txt
password_reset_token-0.0.4.dist-info/RECORD
