Metadata-Version: 2.1
Name: password-reset-token
Version: 0.0.4
Summary: Simple and easy to use Python 3 module to generate password reset tokens, based on JWT.
Author: Valtteri Remes
Classifier: Programming Language :: Python :: 3
Classifier: License :: OSI Approved :: MIT License
Requires-Python: >=3.6
License-File: LICENSE
Requires-Dist: PyJWT (==2.4.0)
